mytweets/__init__.py
mytweets/api/__init__.py
mytweets/api/bookmarks.py
mytweets/api/likes.py
mytweets/api/user_id.py
mytweets-0.1.0.dist-info/WHEEL
mytweets-0.1.0.dist-info/METADATA
mytweets-0.1.0.dist-info/RECORD
