Metadata-Version: 2.1
Name: mytweets
Version: 0.1.0
Summary: 
Author: yrcmpbll
Author-email: yuri.campbell@gmail.com
Requires-Python: >=3.8,<4.0
Classifier: Programming Language :: Python :: 3
Classifier: Programming Language :: Python :: 3.10
Classifier: Programming Language :: Python :: 3.8
Classifier: Programming Language :: Python :: 3.9
Requires-Dist: oauthlib (>=3.2.0,<4.0.0)
Requires-Dist: requests-oauthlib (>=1.3.1,<2.0.0)
